geom_parameters/__init__.py
geom_parameters/measures.py
geom_parameters/mirror.py
geom_parameters/sort_atropo.py
geom_parameters/split.py
geom_parameters/const_func/__init__.py
geom_parameters/const_func/argparse_class.py
geom_parameters/const_func/calc.py
geom_parameters/const_func/io.py
geom_parameters/func/__init__.py
geom_parameters/func/argparse_class.py
geom_parameters/func/calc.py
geom_parameters/func/io.py
geom_parameters/stand_alone/__init__.py
Geometrical_Parameter-1.0.1.dist-info/LICENSE
Geometrical_Parameter-1.0.1.dist-info/METADATA
Geometrical_Parameter-1.0.1.dist-info/WHEEL
Geometrical_Parameter-1.0.1.dist-info/entry_points.txt
Geometrical_Parameter-1.0.1.dist-info/top_level.txt
Geometrical_Parameter-1.0.1.dist-info/RECORD
