Metadata-Version: 2.1
Name: Geometrical-Parameter
Version: 1.0.1
Summary: ['', 'Geometrical_Parameters', 'Geometrical parameters from xyz files. ', '', 'To know how to use it, visit our github reopository: https://github.com/Asymmetric-Lab/Geometrical_Parameters', '', '']
Home-page: https://github.com/Asymmetric-Lab/Geometrical_Parameters
Author: Asymmetric Lab development team
Author-email: andrea.pellegrini15@unibo.it
Maintainer: Asymmetric Lab team
Maintainer-email: andrea.pellegrini15@unibo.it
License: MIT License
Platform: Any.
Classifier: Development Status :: 5 - Production/Stable
Classifier: Environment :: Console
Classifier: Intended Audience :: Science/Research
Classifier: Intended Audience :: Developers
Classifier: License :: OSI Approved :: BSD License
Classifier: Natural Language :: English
Classifier: Operating System :: OS Independent
Classifier: Programming Language :: Python
Classifier: Topic :: Scientific/Engineering :: Chemistry
Classifier: Topic :: Software Development :: Libraries :: Python Modules
License-File: LICENSE
Requires-Dist: numpy
